apyum/__init__.py
apyum/endpoint.py
apyum/exceptions.py
apyum/main.py
apyum/middleware.py
apyum/service.py
apyum/starter.py
apyum/utils.py
apyum-0.1.2.dist-info/LICENSE
apyum-0.1.2.dist-info/METADATA
apyum-0.1.2.dist-info/WHEEL
apyum-0.1.2.dist-info/entry_points.txt
apyum-0.1.2.dist-info/top_level.txt
apyum-0.1.2.dist-info/RECORD
