Metadata-Version: 2.1
Name: apyum
Version: 0.1.2
Summary: Adapter for Celery that implements JSON-RPC 2.0 protocol.
Home-page: https://github.com/aiselis/apyum
Author: Alessio Pinna
Author-email: alessio.pinna@aiselis.com
Maintainer: Alessio Pinna <alessio.pinna@aiselis.com>
License: Apache 2
Project-URL: Bug Reports, https://github.com/aiselis/apyum/issues
Project-URL: Source, https://github.com/aiselis/apyum
Platform: UNKNOWN
Classifier: License :: OSI Approved :: Apache Software License
Classifier: Intended Audience :: Developers
Classifier: Programming Language :: Python
Classifier: Programming Language :: Python :: 3
Classifier: Programming Language :: Python :: 3.8
Classifier: Programming Language :: Python :: 3.9
Classifier: Development Status :: 3 - Alpha
Classifier: Operating System :: OS Independent
Classifier: Framework :: AsyncIO
Requires-Python: >=3.8
Requires-Dist: celery
Requires-Dist: aiohttp
Requires-Dist: pyyaml
Requires-Dist: jsonschema
